Workbook

Sheet Product Backlog
A1: ID | B1: Title | C1: Description | D1: Acceptance Criteria (most important) - limitations, details of the information, etc | E1: Assigned To | F1: Completed? | G1: User Story Points | H1: Priority | I1: Change | J1: UBS feedback | K1: Test cases | L1: Notes
A2: Foundation
A3: F0 | B3: System Architecture Design | C3: Design the ai agents and other services needed to fullfill the user stories requirements | E3: Denise | F3: Yes | H3: Must | I3: Unchanged
A4: F1 | B4: Data contracts | C4: Shared Pydantic models every module passes to each other (architecture §4). Depends on: F0. | D4: • RequestContext, RiskAssessment, TaskPlan, AgentResult, ActionCommand, Receipt and AuditEvent exist in backend/app/schemas/ • Every field in architecture §4 and §6.3 is present and typed; enums use Literal types • AgentResult.status includes needs_clarification with a question field • SSE event models cover status, answer (with sections[]), action_required, done and error • Unit tests build one valid and one invalid example of each model • Merged in one PR, approved by all developers [NEW] Ticket, TicketSummary, RequestCategory, MeetingNote and Brief models exist [NEW] RequestContext carries role: guest, customer or rm How to build: 1. Copy each JSON example from architecture §4 into a Pydantic model 2. Add the SSE event models next to the existing ones in schemas/chat.py 3. Write a round-trip test per model 4. Open one PR and get all developers to review | E4: Denise | F4: Built - check | H4: Must | I4: Updated | J4: #5 | L4: Built 28 Oct: Ticket/category models in app/schemas/tickets.py (not in contracts.py, so no all-dev PR needed)
A5: F2 | B5: Operational database and synthetic seed | C5: Business tables with RLS, plus fake data for Alex, Michelle and David. Depends on: F0. | D5: • Schemas banking, compliance, rm, consent, conversation, actions, support, notify and events migrate cleanly on the hosted project • RLS is enabled on every customer table; a signed-in customer reads only their own rows • Seed includes Alex's card ending 4821, the $2,400 charge and the pending landlord transfer • Seed includes Michelle's compliance case, requested documents and deadline • Seed includes David's old and new RM, advisor working hours and an open request • Synthetic data only; no service-role key in the app or browser • Migration numbering rule is written in the README How to build: 1. Write one migration per schema in backend/supabase/migrations/ 2. Add RLS policies keyed on customer_id 3. Write a seed migration for the three personas 4. Test RLS by signing in as each persona and reading another persona's rows | E5: Denise | F5: Yes | H5: Must | I5: Unchanged | L5: New persona data goes in F2b, so this story stays closed
A6: F2b | B6: RM, ticket and meeting-note seed data | C6: Synthetic data for the new personas: Sophie (RM), her book of clients, tickets and past meeting notes. Depends on: F2. | D6: • Sophie has an RM account with role rm and a book of clients: Michelle, David and at least 2 more synthetic clients • At least one client (e.g. Alex) belongs to another RM, for access tests • David is an inherited client: previous RM Rachel, 2–3 past meeting notes written by Rachel, one open request and a consent-shared handover note • Michelle has her compliance case plus a card, a suspicious charge and a pending payment (reuse Alex's seed rows) • 8–10 open tickets across Sophie's book with mixed categories and urgency, including one P0 suspected fraud and one breaching its target time • Synthetic data only; RLS tests pass for Sophie, Michelle and David How to build: 1. Add rm.book and rm.meeting_notes tables 2. Write a seed migration for Sophie's book, tickets and notes 3. Move Alex's card and payment rows to Michelle, or copy them 4. Test RLS by signing in as Sophie and reading a client outside her book | F6: Built - check | G6: 3 | H6: Must | I6: New | J6: #3 | K6: Data for all R cases | L6: Built 28 Oct: Partly: Michelle card 7310 + demo tickets; RM/Sophie seed still open
A7: F3 | B7: Audit Log Service | C7: Append-only, tamper-evident record of who did what. Depends on: F1, F2. | D7: • audit.events can only be written through audit.record() (SECURITY DEFINER) • UPDATE, DELETE and TRUNCATE are revoked from all app roles • Each row stores prev_hash and hash; editing a row breaks the chain and a check script detects it • A generic trigger records insert/update/delete on audited business tables • State changes write their audit row in the same transaction • A failed audit write fails the request • Events hold ids, enums and counts only, never user text or customer records How to build: 1. Create the audit schema, table and record() function 2. Add the hash chain and a verify script 3. Attach the row trigger to business tables 4. Add a Python helper that batches events per request | E7: Denise | F7: Yes | H7: Must | I7: Unchanged | J7: #7 | L7: Reused for the audit trail walkthrough (F24)
A8: F4 | B8: API Gateway Layer | C8: Entry point that checks who is calling and builds the RequestContext. Depends on: F1, F3. | D8: • JWT is verified with cached JWKS; invalid or expired tokens get 401 • customer_id comes only from the JWT, never from the request body • Guests get a guest principal with no customer_id • Rate limit and payload size limit return stable error codes • auth.session_started is recorded the first time a session_id is seen • POST /auth/session-end records auth.session_ended • Every request has a request_id passed to all modules How to build: 1. Move JWT checks from core/auth.py into middleware 2. Build RequestContext and attach it to the request 3. Add the in-process token-bucket rate limit 4. Add the session-end endpoint and audit events | E8: Denise | F8: Yes | H8: Must | I8: Unchanged
A9: F5 | B9: Input Guardrail | C9: Rule-based check of every message before any AI runs. Depends on: F1. | D9: • Returns a RiskAssessment for every message • Never calls the LLM • Card numbers, passwords, OTPs and NRIC are redacted and counted • Lost card, shared secrets and human-support requests return fixed responses • Guest asking about 'my balance' gets the log-in fixed response • Fraud wording sets fraud_suspected and priority P0 • Shared privacy fixtures pass in backend and frontend; ordinary password-reset questions are unchanged • Never asks for PIN, password, OTP, CVV or full card number; if the customer types one, warns them and never repeats it back (from X2) How to build: 1. Merge privacy.py and safety.py behind one guard() function 2. Add fraud wording rules and priority 3. Keep frontend lib/chatTools.js redaction in sync 4. Extend tests/fixtures/privacy-cases.json | E9: Deshaun | F9: Yes | H9: Must | I9: Unchanged | J9: #1 | K9: C02, C06
A10: F6 | B10: LLM Gateway | C10: One model client for the planner and all agents. Depends on: F1. | D10: • Planner and agents all call the model through this client • Prompts load by agent and version from prompts/<agent>/vN • Output is parsed against a strict JSON schema • Timeouts, limited retries and a per-request token budget are enforced • Errors are reported, never replaced with a sample answer • Model, tokens and latency are recorded per call with a trace span • Released prompt versions are never edited; each new version has a prompt-log entry How to build: 1. Wrap the existing services/llm.py call in a generic client 2. Extend services/prompts.py to load per-agent folders 3. Add timeout, retry and budget settings to core/config.py 4. Record token and latency in the trace tables | E10: Denise | F10: Yes | H10: Must | I10: Unchanged | J10: #6 | L10: Trace spans also sent to LangSmith in F22
A11: F7 | B11: Conversation Store | C11: Saves chats so follow-ups and returning customers keep context. Depends on: F2, F4, F5. | D11: • Each turn is saved with redacted text only • A follow-up in the same chat sees the earlier turns • A signed-in customer can list and reopen only their own chats (RLS) • Cases group the tasks from one conversation • LangGraph checkpoints are stored here • Guest sessions expire • Follow-ups such as 'what about the other one?' resolve to the right topic, and topics are kept separate • A signed-in customer can resume from where they left off in their last chat (from X1) [NEW] A record of what the client was told (bot statements and uploads, with dates) can be read by their RM through the Customer Data Service, subject to authorisation (for RM8) How to build: 1. Create conversation.sessions, messages, cases and checkpoints 2. Save each turn after the guardrail 3. Load history at the start of each turn 4. Add an endpoint to list previous chats | E11: Deshaun | F11: No | H11: Must | I11: Updated | J11: #7
A12: F8 | B12: Knowledge Service | C12: Moves the article library into Supabase with full-text search. Depends on: F2. | D12: • kb.articles, kb.sections and kb.facts exist with read-only RLS • kb.search() returns ranked sections cited as article_id@vN#anchor • Unrelated questions return no sections • get_fact() returns exact fees, limits and rates • knowledge.py reads from Supabase; today's answers still pass the offline evaluation • External articles have reference_url, checked_on, review_due and an allowed domain [NEW] Policy articles exist for every request category in F20 (e.g. card limit: documents needed, who decides, typical turnaround) How to build: 1. Write the kb migration from knowledge-base-design.md 2. Move current in-memory articles into a content migration 3. Write the kb.search() SQL function 4. Point knowledge.py at the RPC and rerun the evaluation | E12: Deshaun | F12: Built - check | H12: Must | I12: Updated | J12: #4 | L12: Built 28 Oct: card-limit-change article (memory + migration 0071)
A13: F9 | B13: Authorisation & Consent Service | C13: One place that decides whether a read or action is allowed. Depends on: F2, F3. | D13: • decide() returns allow, reasons and obligations (mask, require confirmation, require consent) • Guests are denied all personal data • An agent calling a tool outside its allow-list is denied • card.unblock requires step-up (aal2) • Auto vs confirm action types are listed in the policy rules • has_consent() respects expiry and revocation • Every decision writes a policy.decision audit event How to build: 1. Write policy rules as Python in services/authorisation.py 2. Create consent.grants with RLS 3. Add has_consent() 4. Test each rule with allow and deny cases | E13: Deshaun | F13: Yes | H13: Must | I13: Unchanged | J13: #1 | K13: C06
A14: F9b | B14: RM role and book-based access | C14: Authorisation rules for staff users, so an RM sees only her own clients. Depends on: F4, F9. | D14: • RM principal comes from JWT claims (role = rm, rm_id); never from the request body • An RM can read only clients in her book; any other client is denied and audited • An RM sees the client's handover note only with an active consent grant • An RM cannot run client-side actions (e.g. card block) or change ticket status through the bot • Every decision writes a policy.decision audit event How to build: 1. Add the rm role and rm_id claim 2. Add book-based rules to services/authorisation.py 3. Add RLS policies on rm and support tables 4. Test allow and deny cases for Sophie | F14: No | G14: 3 | H14: Must | I14: New | J14: #1, #7 | K14: R05, R06
A15: F10 | B15: Customer Data Service | C15: The only way agents read customer records. Depends on: F2, F9. | D15: • Functions exist for profile, accounts, transactions, credit cards, loans, compliance case, RM assignment, requests and free slots • Every query filters by customer_id in code and runs with the user JWT so RLS applies • Card numbers show last 4 only; account numbers and NRIC are masked • Every call asks decide() first • Every result returns a call_id the validator can check figures against • Every call writes a data.read audit event • No service-role key is used How to build: 1. Create services/customer_data.py with one function per read 2. Add masking helpers 3. Return {call_id, data, as_of} 4. Write RLS tests per persona | E15: Denise | F15: Yes | H15: Must | I15: Unchanged | J15: #1
A16: F10b | B16: RM data functions | C16: Read functions the RM Assistant uses. Depends on: F9b, F19. | D16: • Functions exist for: list my book, client profile summary, open tickets, ticket history, meeting notes, review status, what the client was told • Every call asks decide() first and writes a data.read audit event • Every result returns a call_id the validator can check facts against • Masking rules from F10 apply How to build: 1. Add services/rm_data.py with one function per read 2. Return {call_id, data, as_of} 3. Write RLS tests for Sophie | F16: No | G16: 3 | H16: Must | I16: New | J16: #6
A17: F11 | B17: Action Service core | C17: run_action(): the single path for every change. Depends on: F3, F9. | D17: • Confirm-type actions stop as proposed and send action_required • Proposed commands expire after 5 minutes; an expired confirm executes nothing • A repeated request or confirm returns the same receipt • Policy is re-checked at confirm time • Change, outbox row and audit event commit in one transaction • Every executed action returns a receipt • The model can never choose or call an executor directly • POST /commands/{id}/confirm works How to build: 1. Create actions.commands with idempotency_key 2. Write run_action() with the seven steps from architecture §5.7.3 3. Add the executor registry 4. Add the confirm endpoint | F17: Yes | H17: Must | I17: Unchanged | J17: #2
A18: F12 | B18: Card and handoff executors | C18: Card blocking and passing a case to a person. Depends on: F11. | D18: • Card block runs only after the customer confirms • Allowed transitions are active → temporarily_blocked → active / cancelled; others are rejected • Unblock and permanent cancel are staff-only • Handoff includes a redacted case summary • Only one open handoff per case and reason • Handoff queue orders P0 first, then age • RLS tests pass How to build: 1. Write services/actions/cards.py 2. Write services/actions/handoffs.py and support.handoffs 3. Register both in the executor registry 4. Add a staff script to claim and close handoffs | F18: Yes | H18: Must | I18: Unchanged | J18: #5 | L18: Handoffs will create a ticket through F19
A19: F13 | B19: Appointment and records executors | C19: Bookings, consent and record updates. Depends on: F9, F11. | D19: • A slot hold lasts 10 minutes • Two bookings on the same slot cannot both succeed (exclusion constraint) • Booking is confirmed only after the customer confirms • Sharing a summary or agenda fails without an active consent grant • Consent grants and revocations are written only here, each with a receipt • Checklist update, agenda save and consent request run without confirmation How to build: 1. Write services/actions/appointments.py and the booking table 2. Write services/actions/records.py 3. Register all types with their auto/confirm setting 4. Test double booking and missing consent | F19: Yes | H19: Must | I19: Unchanged
A20: F14 | B20: Conversation Orchestrator | C20: Splits a message into tasks, runs agents and merges one reply. Depends on: F5, F6, F7, F16. | D20: • Several issues in one message become separate tasks • Clear single-intent messages are planned by rules without an LLM call • Tasks are ordered P0 fraud > P1 security > P2 deadline > P3; guardrail flags override • Independent tasks run in parallel with a timeout each • Reply has one section per task in priority order • Loan and fee sections get the disclaimer • Conversation pauses for confirmation and resumes from the checkpoint • A failed agent withholds only its own section • Runs behind PIPELINE=v2; PIPELINE=v1 runs today's chatbot unchanged • The chat states it is an AI at the start, and that answers are general information, not advice or a contract (from X3) [NEW] Routes by role: client and RM requests run through the same graph, each with its own agents [NEW] Messages matching a request category (F20) follow that category's flow [NEW] A task the bot cannot resolve ends as a ticket (F19) or a handoff, never a dead end [NEW] No node approves, rejects or decides a request; decisions are only recorded from people How to build: 1. Add the PIPELINE setting 2. Build the LangGraph graph with plan, prioritise, dispatch, compose 3. Add the Postgres checkpointer and interrupt on proposed actions 4. Resume the graph from the confirm endpoint | F20: Built - check | H20: Must | I20: Updated | J20: #2, #4, #5 | K20: C03, C04 | L20: Built 28 Oct: Category hand-offs and ticket-on-escalation via 0071 triggers; RM routing still open
A21: F15 | B21: Response Validator | C21: Checks each section before it is shown. Depends on: F8, F10, F11, F14. | D21: • Sections without valid sources are withheld • Source ids exist and match the allowed scope • Figures match kb.facts or a Customer Data result • 'Blocked' / 'done' wording appears only with a receipt • No secrets, URLs or prompt text leak • Failure → section withheld, origin validation, needs_human=True and a handoff • Other sections are still released • Each section shows its source (FAQ / help page), collapsed by default; a declined answer gives a short reason (from X5) [NEW] A failed section is retried or repaired once with the validator's feedback before it is withheld and handed off [NEW] Ticket summaries and briefs are checked: every fact maps to a ticket event, note or record id [NEW] No approve or reject wording passes the validator How to build: 1. Extend source_checks.py to run per section 2. Pass tool results and receipts into the validator 3. Create a handoff on failure 4. Add tests for each failure type | F21: Built - check | H21: Must | I21: Updated | J21: #6 | K21: R09, R10 | L21: Built 28 Oct: Repair attempt already existed (agents/answer.py); validation failures now also open a ticket
A22: F16 | B22: Stub Agents | C22: Minimal version of each of the five agents for the user stories to build on. Depends on: F1, F6, F9. | D22: • Everyday Banking, Fraud & Security, Compliance Review, Document Check and Relationship agents exist • Each has a prompt v1 folder and a prompt-log entry • Each has its tool allow-list from architecture §5.6 • Each returns a valid AgentResult from the real provider, never a fixed sample answer • An out-of-scope request returns to the orchestrator • The orchestrator can dispatch a task to every agent [NEW] A sixth agent, RM Assistant, exists with tools: book, tickets, ticket history, meeting notes, review status, what the client was told [NEW] RM Assistant can only read and draft; it never sends, closes or changes anything How to build: 1. Create services/agents/ with one file per agent 2. Write a short v1 prompt per agent 3. Register agents and allow-lists 4. Add a live test that calls each agent once | F22: No | H22: Must | I22: Updated | J22: #3
A23: F17 | B23: Local deployment | C23: Run the whole app locally with one command. Depends on: F4, F14. | D23: • docker compose up starts web and api against the hosted Supabase project • The chatbot works end to end in the browser • Secrets come from .env only and are not baked into images or committed • README explains how to start and stop it How to build: 1. Write Dockerfiles for frontend and backend 2. Write docker-compose.yml with env_file 3. Document the steps in README | F23: Built - check | H23: Should | I23: Unchanged | L23: Built 28 Oct: docker-compose.yml + Dockerfiles (not run in the build environment)
A24: F18 | B24: Hardening and report evidence | C24: Check the foundation is safe and fast before persona work builds on it. Depends on: F1–F17. | D24: • RLS checks pass for all three personas • Audit hash chain verifies with no gaps • Every request has trace spans per node, agent and tool • Playwright smoke test of PIPELINE=v2 passes with the real provider • Latency per request type is measured against the architecture budget • Results and limitations are written up for the report • An evaluation set of informal, misspelled, ambiguous and rephrased questions passes for every persona (from EB7) [NEW] RLS checks also pass for Sophie (RM) and for a client outside her book [NEW] Evaluation results come from the LangSmith harness (F22) How to build: 1. Write RLS and audit test scripts 2. Add trace spans to the orchestrator and agents 3. Write the Playwright smoke test 4. Run, record and write up results | F24: No | H24: Must | I24: Updated | J24: #6
A25: F19 | B25: Ticket Service | C25: One place to create and track tickets in the backend, for the client and the RM. Depends on: F1, F2b, F3, F11. | D25: • create_ticket() takes category, details, urgency, attachments and a redacted conversation summary, and returns a reference (e.g. TCK-000123) • Owner team and target time are set from the category (F20) • Status flow: submitted → in review → waiting on client → resolved → closed; only staff or the RM change status • The bot never marks a ticket resolved or closed • Client-facing status is plain language and never shows internal notes • An open ticket with the same client and category is shown instead of creating a duplicate • A ticket past its target time is flagged as breaching • Every create and status change writes an audit event in the same transaction • The handoff executor (F12) creates a ticket How to build: 1. Create support.tickets and support.ticket_events 2. Write services/tickets.py and register create_ticket as a confirm-type action 3. Add status and duplicate rules 4. Test with Michelle's and Sophie's data | F25: Built - check | G25: 5 | H25: Must | I25: New | J25: #5, #7 | K25: C04, R01 | L25: Built 28 Oct: Migration 0071 + api/tickets.py; native tests in test_tickets.py
A26: F20 | B26: Request Category Catalogue | C26: Fixed request categories that guide the conversation without the bot deciding anything. Depends on: F8, F19. | D26: • 6–8 categories: card limit change, statement request, personal details update, payment or transfer issue, login or access issue, compliance documents, suspected fraud, request to RM • Each category defines: required fields, follow-up questions, documents needed, owner team, who decides, target time • The bot asks only for fields that are still missing • 'Who decides' is always a person or team, never the bot • Categories are stored as versioned config, not in prompts How to build: 1. Write categories in a config file or table 2. Link each to its policy article (F8) 3. Use it in the orchestrator (F14) and Ticket Service (F19) | F26: Built - check | G26: 3 | H26: Must | I26: New | J26: #4, #2 | K26: C04, R08 | L26: Built 28 Oct: support.request_categories (9 categories) in 0071
A27: F21 | B27: MCP Tool Layer | C27: Expose our tools as local MCP servers so every agent calls them the same way. Depends on: F8, F10, F10b, F19. | D27: • Local MCP servers expose customer data, RM data, knowledge search, tickets, calendar and documents • Agents call tools only through the MCP client • Allow-lists and decide() are still enforced on the server side • Every call carries the request_id and appears as a trace span • Direct calls are removed or kept behind a flag How to build: 1. Wrap existing service functions as MCP tools 2. Point agents at the MCP client 3. Check traces show each tool call | F27: Built - check | G27: 5 | H27: Should | I27: New | J27: #6 | L27: Built 28 Oct: services/tools.py + app/mcp_server.py + scripts/mcp_server.py; TOOL_TRANSPORT=mcp
A28: F22 | B28: LangSmith Tracing and Evaluation Harness | C28: Run our test cases automatically and score them. Depends on: F14, F15, F16. | D28: • Every run is traced to LangSmith with node, agent and tool spans, linked by request_id • Only redacted text is sent to LangSmith • A dataset holds the 20 test cases (C01–C10, R01–R10) in the agreed template • Evaluators: schema (structure, required fields), competency (LLM-as-judge with a written rubric), trajectory (expected nodes, agents and tools, in order) • One command runs all cases and outputs pass rate per evaluator and per persona • Results table and 2 example traces (one pass, one fail + fix) ready for the slides How to build: 1. Add LangSmith env settings and tracing 2. Load test cases into a dataset 3. Write the three evaluators 4. Write the run script with evaluate() | F28: No | G28: 5 | H28: Must | I28: New | J28: #6 | K28: All
A29: F23 | B29: Model Comparison and Consistency Tests | C29: Compare models and check results are stable. Depends on: F22. | D29: • The same dataset runs on 2–3 OpenRouter models • For each model: pass rate, average latency, tokens and cost per conversation • Each case runs 3 times; triage, priority order and guardrail results must match every time • Results and the chosen model are written up for the report | F29: No | G29: 3 | H29: Should | I29: New | J29: #6
A30: F24 | B30: Audit Trail Walkthrough (administrator view) | C30: Show how an administrator or compliance officer traces a decision, without building an admin app. Depends on: F3, F19, F22. | D30: • A script rebuilds one request end to end: chat turn → plan → agents → tools → validation → confirmation → receipt → ticket → audit events • Output is a readable timeline with request_id, times, actors and decisions • The audit hash chain verifies with no gaps • One sample is used in the slides and report • Out of scope: an admin user interface | F30: Built - check | G30: 2 | H30: Must | I30: New | J30: #7 | K30: R03 | L30: Built 28 Oct: Migration 0072 + scripts/audit_walkthrough.py
A31: QA1 | B31: Test Case Set (template + 20 cases) | C31: Write and maintain the test cases the evaluation harness runs. Depends on: personas agreed. | D31: • Every case uses the agreed template: ID, persona, category, type, priority, backlog story, UBS feedback, owner, setup, input, orchestrator steps, specialist agents, tools, agent-level checks, priority order and escalation, expected output, must not happen, hand-off, checks and pass criteria, run record • 10 cases for Michelle (C01–C10) and 10 for Sophie (R01–R10), updated from Alex/Marcus to the new personas • Mix per persona: about 4 normal, 3 guardrail, 2 edge and 1 attack • Every Must story has at least one case (see the Test cases column); every UBS feedback point is covered • Each case has an owner and is re-run after any fix, with the result recorded | F31: No | G31: 3 | H31: Must | I31: New | J31: #6 | K31: All
A32: CC | B32: Common acceptance criteria (apply to every story) | C32: Shared rules every chatbot story must meet, written once instead of repeated in each story. | D32: - Asks a clarifying question when the request is unclear or missing details, instead of guessing. - Answers only from approved knowledge or the customer's own records; never invents figures, fees, dates or procedures. - When it cannot help, says so and directs the customer to the right official channel or a person, with the conversation context. - A "Talk to a person" option is available at any point. - Does not give personalised investment, legal or tax advice, and says so when asked. [NEW] Never approves, rejects or decides a request, and says who does. [NEW] Checks the user is signed in (with MFA where required) before anything account-specific; general questions need no sign-in. [NEW] Anything it cannot resolve ends as a ticket with a reference number, raised only after the user confirms. [NEW] Every reply is traceable: one request_id links the chat, trace, audit events and any ticket. [NEW] Client messages written by the bot for an RM are drafts until the RM approves them. | F32: Built - check | H32: Must | I32: Updated | J32: #1, #2, #5, #6 | K32: C05, C10, R08 | L32: Built 28 Oct: Never decides, ticket on unresolved, request_id traceability
A33: Persona 1 - Michelle, Time-Poor Wealth Client (merges old personas 1–3, client side)
A34: CR1 | B34: Personalised Document Checklist | C34: As a client responding to a compliance review, I want the chatbot to list the documents requested in my notice and show which are still outstanding, so that I can prepare and submit everything without overlooking a requirement. | D34: - Given a compliance notice, the chatbot lists each document explicitly requested, with submission instructions from the notice or approved guidance. - The chatbot does not add document requirements that are not in the notice. - Each item shows one status: not prepared, prepared, submitted – awaiting review, or unknown; an unknown status is never shown as missing. - The client can mark items as prepared or not prepared, and the checklist updates straight away. - A document is never shown as accepted unless the authorised system confirms acceptance. - If the notice is incomplete or unclear, the chatbot recommends contacting the bank. | E34: Deshaun | F34: Yes | H34: Must | I34: Moved | K34: C07 | L34: Core need
A35: CR7 | B35: Upload a Document | C35: As a client responding to a compliance review, I want to upload a requested document through the chatbot, so that I can submit it without visiting a branch or emailing it. | D35: - A logged-in client can upload a file against a checklist item. - Allowed formats and size limits are shown before upload; other files are rejected with a clear message. - Uploaded files are stored privately and can be read only by the client and the bank. - After a successful upload, the checklist item shows submitted – awaiting review. | E35: Deshaun | F35: No | H35: Must | I35: Moved | K35: C08 | L35: Core need
A36: CR2 | B36: AI-Assisted Document Pre-Check | C36: As a client submitting supporting documents, I want the chatbot to identify potential document issues immediately, so that I can correct them before formal review instead of waiting several working days to learn that something is missing or unsuitable. | D36: - For an uploaded document, the system checks that the file opens, the page count matches what is expected, and the required fields are present. - For each issue found, the chatbot explains what is wrong and how to fix it, in the same chat. - If the document cannot be assessed reliably (e.g. not legible), the chatbot says so instead of giving a result. - The result is labelled as a preliminary check, not formal compliance approval. [NEW] Flags documents that are expired, unclear, or may need translation or certification (e.g. foreign-issued) | E36: Deshaun | F36: Built - check | H36: Must | I36: Updated | K36: C08 | L36: Core need | Built 28 Oct: translation_needed finding (notice_checks.py)
A37: CR4 | B37: Compliance Status & Information Requests | C37: As a client in a compliance review, I want to see the latest review status, what I still need to do, and any further information the bank has asked for, so that I can respond without unnecessary delays. | D37: - Given an available review record, the chatbot shows the latest status and the date it was last updated. - The status separates actions required from the client from actions pending with the bank. - If status information is unavailable or outdated, the chatbot says so instead of inventing progress. - For each recorded request for more information, the chatbot explains in plain language what is being asked. - If the reason for a request is unclear, the chatbot does not speculate and directs the client to the support team. | E37: Deshaun | F37: Yes | H37: Must | I37: Moved | K37: Gap: add case | L37: Core need
A38: CR6 | B38: Review Deadline Reminders | C38: As a client with a pending compliance request, I want to receive reminders of relevant deadlines and outstanding actions, so that I can respond within the required timeframe. | D38: - Given an authorised deadline and an outstanding action, the system can generate a reminder according to its configured notification rules. - The reminder identifies the outstanding action and the applicable deadline. - The chatbot does not invent a deadline when none is recorded. - The client is directed to the approved channel for completing the outstanding action. - Reminders are sent only through supported channels and in accordance with the applicable notification preferences and privacy requirements. | E38: Deshaun | F38: Yes | H38: Should | I38: Moved
A39: EB1 | B39: Login | C39: As a customer, I want to securely log in to my banking account so that I can access personalised account information and interact with the chatbot. | D39: - The system provides a login page where customers enter their email address and password. - Upon successful login, customers are redirected to the chatbot interface. - If incorrect login credentials are entered, the system displays an appropriate error message. - Unauthenticated customers cannot access personalised account information. - The login session lasts until the customer logs out or the session expires; logging out ends access to personalised information until they log in again. | E39: Kar Mun | F39: Yes | H39: Must | I39: Moved | J39: #1
A40: EB6 | B40: Product & Service Information (no sign-in) | C40: As a customer, I want to ask about the bank's account products and common services without logging in, so that I can get help without contacting a customer service officer. | D40: - Without login, the chatbot answers general questions about account features, fees, limits and interest. - The chatbot answers common service enquiries, such as fund transfers, updating personal details, requesting statements and accessing online banking. - The chatbot gives clear, step-by-step instructions for common banking procedures, written in plain language. - Where an action has to be done elsewhere, the chatbot links to the right place in the app or website. [NEW] Guest answers never include or ask for personal data; if a question needs her account, the bot asks her to sign in [NEW] Quotes published fees only; fee discussions or negotiations go to her RM | E40: Denise | F40: Built - check | H40: Must | I40: Updated | J40: #1, #3 | K40: C01, C02 | L40: Built 28 Oct: Guest login prompt already existed; fee wording via knowledge
A41: EB8 | B41: Suspicious Charge & Lost Card | C41: As a customer, I want urgent help when I see a charge I don't recognise or my card is lost or stolen, so that I can protect my money quickly. | D41: - The chatbot gives urgent steps first and tells the customer to contact the bank immediately through official channels. - The chatbot offers a temporary card block straight away, blocks the card only after the customer confirms, and then confirms in the chat that the block is active. - Verification and permanent cancellation are sent to a human agent, who handles them when available. - The chatbot explains the next steps, including how to get a replacement card. - The chatbot does not claim to investigate or reverse the charge. [NEW] Raises a P0 ticket to the fraud team with a reference number and notifies her RM | E41: Denise | F41: Built - check | H41: Must | I41: Updated | J41: #5 | K41: C03 | L41: Built 28 Oct: Fraud handoff now opens a P0 ticket automatically
A42: CL1 | B42: Guided Request: Card Limit Change | C42: As Michelle, I want to request a higher card limit through the chatbot and understand what is needed and who decides, so that I don't use my RM's time on routine requests. | D42: - Recognises the card limit category (F20) and asks only for missing details: amount, temporary or permanent, dates, reason. - Lists the documents needed from approved policy. - Summarises the request and asks her to confirm before raising a ticket. - Raises a ticket to the cards team and gives her the reference number and typical turnaround. - Never says the request is approved, rejected or likely to succeed; states who decides. - If she asks the bot to just approve it, it politely refuses and offers her RM. | F42: Built - check | G42: 3 | H42: Must | I42: New | J42: #2, #4, #5 | K42: C04, C05 | L42: UBS's own example | Built 28 Oct: My requests form + chat button; SQL checks card ownership and fields
A43: TK1 | B43: Raise a Ticket | C43: As Michelle, I want the chatbot to log an issue it can't resolve and give me a reference number, so that I know it is being handled without chasing anyone. | D43: - When the bot can't resolve something, it offers to raise a ticket. - It confirms the details with her first; a ticket is never raised without her knowing. - The ticket carries the category, a short issue summary, any documents and the redacted conversation context. - She gets a reference number in the chat. - If the same issue is already open, the bot shows that ticket instead of creating a duplicate. | F43: Built - check | G43: 3 | H43: Must | I43: New | J43: #5 | K43: Gap: add case | L43: Built 28 Oct: ticket.create action, dedup of open requests
A44: TK2 | B44: Ticket Status in Plain Language | C44: As Michelle, I want to ask for the status of my ticket, so that I know where it stands without chasing my RM. | D44: - "What's the status of my ticket?" lists her open tickets with reference, status, last update and next step. - Status is in plain language and never shows internal notes. - Never says an issue is resolved unless the system records it. - If a ticket is past its target time, says so and offers to contact her RM. | F44: Built - check | G44: 2 | H44: Must | I44: New | J44: #5 | K44: Gap: add case | L44: Built 28 Oct: My requests page with plain-language status
A45: HO1 | B45: Hand Off to My RM with Context | C45: As Michelle, I want sensitive or complex matters passed to my RM with the context, so that I never have to repeat myself. | D45: - For investment decisions, fee negotiations, complex transfers or sensitive matters, the bot offers a handoff to her RM. - She sees what will be shared before it is sent. - The RM receives the escalation summary in RM5. - The bot tells her who will contact her and what to expect. | F45: Built - check | G45: 2 | H45: Must | I45: New | J45: #2 | K45: C10 | L45: Built 28 Oct: Existing Talk to a person + automatic ticket
A46: RC4 | B46: Request Intake & Status | C46: As a client, I want to send a request to my relationship manager at any time and check its progress, especially while my relationship manager is changing or unavailable, so that I know it is being handled and who to contact. | D46: - The chatbot collects a structured request: what is needed, urgency and deadline. - The chatbot confirms the request was received, and it appears in the relationship manager's queue. - The client can see each request's latest status (sent, seen, answered) and any action required from them. - The chatbot does not say a request was transferred or completed unless the system records it. - If the status is unavailable, the chatbot gives the follow-up contact channel. | E46: Kar Mun | F46: Yes | H46: Should | I46: Merged | J46: #5 | L46: New client requests now go through TK1/TK2 and the Ticket Service; reuse RC4's status code there
A47: RC1 | B47: Smooth Relationship Manager Transition | C47: As a client whose relationship manager has changed, I want a personalised introduction to my new advisor or advisory team, so that I know who is looking after me and feel confident that my relationship with DemoBank will continue smoothly. | D47: - Given that a new relationship manager has been assigned, the chatbot retrieves the confirmed advisor details from an authorised system. - The chatbot provides the new advisor's name, role and available contact details. - The chatbot explains the change only with approved wording: no invented reasons and no promises the bank has not confirmed. - If the new advisor's details are unavailable, the chatbot directs the client to a support channel. | E47: Kar Mun | F47: Yes | H47: Should | I47: Moved | J47: #1 | L47: Client side of Sophie's inherited-client story
A48: RC2 | B48: Handover Note for New Relationship Manager | C48: As a client moving to a new relationship manager, I want to prepare a short note of my preferences, priorities and the topics I want to discuss, so that my new advisor understands what matters to me and our first meeting is productive. | D48: - The chatbot drafts the note from information that is available and authorised for use. - The client can add the questions and topics they want to discuss; the chatbot organises them into a short agenda within the note. - The client can review and edit the whole note before sharing it. - The chatbot names the recipient and explains how the note will be used. - The note is shared only after the client's consent and the authorisation checks, and the chatbot confirms whether it was shared. | E48: Kar Mun | F48: Yes | H48: Should | I48: Moved | J48: #1 | L48: Feeds Sophie's inherited-client brief (RM7)
A49: RC3 | B49: Instant Meeting Scheduling | C49: As a client with a new relationship manager, I want to view available meeting times and schedule an introductory call through the chatbot, so that I can reconnect with a person conveniently and feel reassured about the transition. | D49: - The chatbot retrieves available appointment slots from an authorised scheduling system. - The client can select a suitable date and time from the available options. - The chatbot confirms the appointment only after the scheduling system confirms the booking. - The confirmation includes the meeting date, time, format and relevant joining details where available. - If direct scheduling is unavailable, the chatbot provides a verified alternative for contacting the advisory team. | E49: Kar Mun | F49: Yes | H49: Should | I49: Moved
A50: EB5 | B50: Failed or Pending Transaction | C50: As a customer, I want to ask about failed or pending transactions so that I can understand the issue and know what to do next. | D50: - The chatbot explains the difference between failed and pending transactions in plain language. - The chatbot gives troubleshooting steps for the type of issue reported. - For logged-in customers, the chatbot explains the issue using their own transaction record. - The chatbot does not claim to reverse, cancel or speed up a transaction. | E50: Denise | F50: No | H50: Should | I50: Moved | K50: C03 | L50: Secondary need: payment status
A51: EB4 | B51: Credit Card Enquiry | C51: As a customer, I want to ask questions about my credit card, such as fees, limits and payment due dates, so that I can manage my card properly. | D51: - The chatbot provides the customer's credit card details, including credit limit, outstanding balance, minimum payment and payment due date. - The chatbot explains applicable credit card fees and charges. - The chatbot explains general credit card concepts, such as minimum payments, interest charges and available credit. - When the customer has more than one card, the chatbot asks which card they mean. [NEW] Requests to change the limit hand over to CL1 | E51: Denise | F51: No | H51: Should | I51: Updated | L51: Limit changes now handled by CL1
A52: EB2 | B52: My Account Information | C52: As a customer, I want to ask about my own accounts, such as balances, recent transactions and fees charged, so that I can understand my account without having to call or visit a branch. | D52: - Before showing any account-specific information, the bot asks the customer to log in. - Once logged in, the bot answers questions about balances, recent transactions, account details and fees charged. - The bot can explain a specific charge or transaction in plain language (e.g. what a fee is for). - Requests the bot cannot do (e.g. closing an account or disputing a transaction) are handed to a person or the right service channel. | E52: Denise | F52: No | H52: Could | I52: Deprioritised | L52: Not a core need for Michelle; build only if time allows
A53: EB3 | B53: Loan Enquiry | C53: As a customer, I want to ask about available loan products, eligibility requirements and application procedures so that I can understand my borrowing options. | D53: - The chatbot explains available loan products, eligibility requirements and application procedures. - The chatbot does not guarantee loan approval and states that the bank makes the final decision. - The chatbot directs the customer to the appropriate banking channel for actual loan applications. | E53: Denise | F53: No | H53: Won't (this round) | I53: Deprioritised | L53: Not in the new persona
A54: DL1 | B54: Authorised Delegate | C54: As Michelle, I want my assistant to submit documents for me with my authorisation, so that I don't handle admin myself. | D54: - Future scope: only mentioned in the presentation. | F54: No | H54: Could | I54: New | J54: #1 | L54: Future
A55: Persona 2 - Sophie, Relationship Manager (new main user)
A56: RM1 | B56: RM Sign-in and Client Book | C56: As Sophie, I want to sign in to an RM view and see my clients, so that I can work on them in one place. | D56: - Sophie signs in as an RM and sees the list of clients in her book. - Clients outside her book cannot be opened, searched or mentioned by the assistant. - The RM view is separate from the client chat. - Note for slides: in practice this would sit inside the RM's existing workspace. | F56: No | G56: 2 | H56: Must | I56: New | J56: #1 | K56: R06
A57: RM2 | B57: Ticket Inbox Ranked by Urgency | C57: As Sophie, I want my open tickets ranked by urgency, so that urgent cases reach me first. | D57: - Lists open tickets for clients in her book only. - Order: P0 fraud or security → breaching target time → deadlines → the rest. - Each row shows client, category, one-line summary, urgency, age or target time, and reference. - "What are my open tickets and which are most urgent?" returns the same list in chat. | F57: No | G57: 3 | H57: Must | I57: New | J57: #5 | K57: R01
A58: RM3 | B58: Ticket Summary | C58: As Sophie, I want any ticket condensed into a short brief, so that I can understand it in under a minute. | D58: - Covers: issue, history, actions taken, what is pending, owner, urgency and a suggested next step. - Every fact links to the ticket event it came from; a link opens the full ticket. - Missing information is flagged, not guessed. - The assistant never closes or changes the ticket. | F58: No | G58: 3 | H58: Must | I58: New | J58: #5, #6 | K58: Gap: add case
A59: RM4 | B59: Draft a Client Update | C59: As Sophie, I want the assistant to draft an update for a client on a ticket, so that I don't write it from scratch. | D59: - The draft uses approved wording and only facts on record. - It is marked Draft; Sophie can edit it. - It is sent only after Sophie approves it. - No promises the bank hasn't confirmed. - The audit log records the draft, her edits, who approved and the text sent; the client sees it through TK2. | F59: No | G59: 3 | H59: Must | I59: New | J59: #2, #7 | K59: R02, R03
A60: RM5 | B60: Escalation Summary | C60: As Sophie, I want every escalation to arrive with a concise summary, so that I can act without calling the client back. | D60: - Includes: who the client is, issues raised, what the bot already said, what is outstanding and a suggested next step. - Links to the ticket and to the redacted conversation summary. - Urgent escalations (e.g. suspected fraud) are marked P0 and appear first in RM2. | F60: No | G60: 3 | H60: Must | I60: New | J60: #5, #6 | K60: Gap: add case
A61: RM6 | B61: Meeting History Summary | C61: As Sophie, I want past meeting notes summarised, including the previous RM's, so that I understand the client's history before we meet. | D61: - Summarises: what was discussed, decisions the client made, promises the bank made, open follow-ups and stated preferences. - Every point cites the note's date and author. - If nothing is on record, says so instead of guessing. - Gives no investment recommendations. | F61: No | G61: 3 | H61: Must | I61: New | J61: #6 | K61: R04, R09
A62: RM7 | B62: Pre-meeting and Inherited-client Brief | C62: As Sophie, I want one brief before a meeting or when I inherit a client, so that our first meeting starts from understanding. | D62: - Combines the meeting history (RM6), open tickets, pending reviews, recent chatbot interactions and what the client was told about the RM change. - Includes the client's handover note (RC2) only with an active consent grant; otherwise shows "Handover note not shared by client". - Flags gaps and suggests questions to ask. - Fits on one screen, with every point linked to its source. | F62: No | G62: 5 | H62: Must | I62: New | J62: #1, #6 | K62: R04, R05
A63: RM8 | B63: What Was the Client Told | C63: As Sophie, I want to see what the chatbot told a client and what they uploaded, so that I can stand behind it. | D63: - Shows the bot's statements and the client's uploads with dates, quoted rather than paraphrased. - Only for clients in her book. | F63: No | G63: 2 | H63: Should | I63: New | J63: #7
A64: RM9 | B64: Pre-filled Bot-raised Tickets | C64: As Sophie, I want tickets raised by the bot to arrive categorised with context, so that nobody has to re-ask the client. | D64: - Bot-raised tickets have category, summary, attachments and conversation context filled in. - Missing required fields are listed on the ticket. | F64: No | G64: 2 | H64: Should | I64: New | J64: #5
A65: RM13 | B65: Meeting Notes into Follow-up Tickets | C65: As Sophie, I want my meeting notes turned into follow-up tickets, so that nothing promised is forgotten. | D65: - Extracts only actions stated in the notes. - Each draft ticket has category, owner team and due date. - Tickets are created only after Sophie confirms each one. | F65: No | G65: 3 | H65: Could | I65: New | J65: #5 | K65: R07
A66: RM10 | B66: Client Review Status at a Glance | C66: As Sophie, I want to see every client's compliance review status and missing documents. | D66: - Future scope: shown in the presentation only. | F66: No | H66: Could | I66: New | L66: Future
A67: RM11 | B67: Proactive Alerts and Daily Digest | C67: As Sophie, I want urgent alerts, a daily digest and reminders for stuck reviews. | D67: - Future scope: shown in the presentation only. | F67: No | H67: Could | I67: New | L67: Future
A68: RM12 | B68: Introductions for Inherited Clients | C68: As Sophie, I want help with a bank-authorised introduction and proposing meeting times. | D68: - Future scope: shown in the presentation only. | F68: No | H68: Could | I68: New | L68: Future

Sheet Summary
A1: Backlog summary
A2: All figures update from the Product Backlog sheet.
A4: Priority | B4: Stories | C4: Not completed | D4: Points not completed
A5: Must | B5: =COUNTIF('Product Backlog'!$H$2:$H$68,A5) -> 45 | C5: =COUNTIFS('Product Backlog'!$H$2:$H$68,A5,'Product Backlog'!$F$2:$F$68,"No") -> 15 | D5: =SUMIFS('Product Backlog'!$G$2:$G$68,'Product Backlog'!$H$2:$H$68,A5,'Product Backlog'!$F$2:$F$68,"No") -> 36
A6: Should | B6: =COUNTIF('Product Backlog'!$H$2:$H$68,A6) -> 12 | C6: =COUNTIFS('Product Backlog'!$H$2:$H$68,A6,'Product Backlog'!$F$2:$F$68,"No") -> 5 | D6: =SUMIFS('Product Backlog'!$G$2:$G$68,'Product Backlog'!$H$2:$H$68,A6,'Product Backlog'!$F$2:$F$68,"No") -> 7
A7: Could | B7: =COUNTIF('Product Backlog'!$H$2:$H$68,A7) -> 6 | C7: =COUNTIFS('Product Backlog'!$H$2:$H$68,A7,'Product Backlog'!$F$2:$F$68,"No") -> 6 | D7: =SUMIFS('Product Backlog'!$G$2:$G$68,'Product Backlog'!$H$2:$H$68,A7,'Product Backlog'!$F$2:$F$68,"No") -> 3
A8: Won't (this round) | B8: =COUNTIF('Product Backlog'!$H$2:$H$68,A8) -> 1 | C8: =COUNTIFS('Product Backlog'!$H$2:$H$68,A8,'Product Backlog'!$F$2:$F$68,"No") -> 1 | D8: =SUMIFS('Product Backlog'!$G$2:$G$68,'Product Backlog'!$H$2:$H$68,A8,'Product Backlog'!$F$2:$F$68,"No") -> 0
A9: Total | B9: =SUM(B5:B8) -> 64 | C9: =SUM(C5:C8) -> 27 | D9: =SUM(D5:D8) -> 46
A11: Change type | B11: Stories
A12: New | B12: =COUNTIF('Product Backlog'!$I$2:$I$68,A12) -> 28
A13: Updated | B13: =COUNTIF('Product Backlog'!$I$2:$I$68,A13) -> 12
A14: Moved | B14: =COUNTIF('Product Backlog'!$I$2:$I$68,A14) -> 9
A15: Merged | B15: =COUNTIF('Product Backlog'!$I$2:$I$68,A15) -> 1
A16: Unchanged | B16: =COUNTIF('Product Backlog'!$I$2:$I$68,A16) -> 12
A17: Deprioritised | B17: =COUNTIF('Product Backlog'!$I$2:$I$68,A17) -> 2
A19: Story points are suggested only for new stories; blank means not estimated yet.

Sheet How to read
A1: How to read this backlog
A3: Priority: Must = needed for the final demo · Should = build if time allows · Could = future scope, mention on slides · Won't = dropped this round
A5: Change: New = new story · Updated = acceptance criteria added (marked [NEW]) · Moved = same story, new persona section · Merged = replaced by newer stories · Unchanged · Deprioritised
A7: Test cases: the test case IDs (from the plan doc's Test cases tab) that prove each story; red 'Gap' = a Must story with no test case yet.
A9: UBS feedback: #1 CID, identity and consent · #2 bot never decides · #3 general help on client side, RM as main user · #4 request categories · #5 tickets to backend · #6 evaluation, testing, traceability · #7 audit trail / administrator view
A11: Fill in Assigned To and Completed? as work progresses. Points for new stories are suggestions.
